[
  {
    "mint": "8Jx8AAHj86wbQgUTjGuj6GTTL5Ps3cqxKRTvpaJApump",
    "symbol": "PENGUIN",
    "name": "Nietzschean Penguin",
    "liquidity": 3544725.3321842733,
    "holderCount": 44873,
    "organicScore": 96.12147648543949,
    "topHoldersPercentage": 17.381357984191805,
    "vol1h": 1638034.8911081443,
    "vol24h": 68148816.21905214,
    "traders1h": 1150,
    "usdPrice": 0.10003647686605087
  },
  {
    "mint": "27G8MtK7VtTcCHkpASjSDdkWWYfoqT6ggEuKidVJidD4",
    "symbol": "JLP",
    "name": "Jupiter Perps",
    "liquidity": 15738399.593320662,
    "holderCount": 91541,
    "organicScore": 97.92818655132542,
    "topHoldersPercentage": 26.507016791503666,
    "vol1h": 1005962.6971554806,
    "vol24h": 48489635.463680714,
    "traders1h": 486,
    "usdPrice": 4.613836678205017
  },
  {
    "mint": "61Wj56QgGyyB966T7YsMzEAKRLcMvJpDbPzjkrCZc4Bi",
    "symbol": "COPPERINU",
    "name": "copper inu",
    "liquidity": 1250212.4877627895,
    "holderCount": 11895,
    "organicScore": 94.3174649506187,
    "topHoldersPercentage": 20.710867392299072,
    "vol1h": 2266412.6122475774,
    "vol24h": 37403088.714729145,
    "traders1h": 2172,
    "usdPrice": 0.014830496213447354
  },
  {
    "mint": "Dfh5DzRgSvvCFDoYc2ciTkMrbDfRKybA4SoFbPmApump",
    "symbol": "pippin",
    "name": "Pippin",
    "liquidity": 7729065.25727639,
    "holderCount": 34679,
    "organicScore": 85.69274551769954,
    "topHoldersPercentage": 28.68135390084599,
    "vol1h": 1121126.5238097114,
    "vol24h": 34806171.58700765,
    "traders1h": 336,
    "usdPrice": 0.4471358918811396
  },
  {
    "mint": "cbbtcf3aa214zXHbiAZQwf4122FBYbraNdFqgw4iMij",
    "symbol": "cbBTC",
    "name": "Coinbase Wrapped BTC",
    "liquidity": 20579303.037888404,
    "holderCount": 55660,
    "organicScore": 93.95047604748243,
    "topHoldersPercentage": 33.59479167358905,
    "vol1h": 1072893.1192274047,
    "vol24h": 31761149.70311551,
    "traders1h": 219,
    "usdPrice": 89042.36290368471
  },
  {
    "mint": "9BB6NFEcjBCtnNLFko2FqVQBq8HHM13kCyYcdQbgpump",
    "symbol": "Fartcoin",
    "name": "Fartcoin",
    "liquidity": 8298775.891137448,
    "holderCount": 166782,
    "organicScore": 96.75638730795762,
    "topHoldersPercentage": 28.022870582418342,
    "vol1h": 913920.4322727539,
    "vol24h": 13625783.076397797,
    "traders1h": 777,
    "usdPrice": 0.30896962178019394
  },
  {
    "mint": "SKRbvo6Gf7GondiT3BbTfuRDPqLWei4j2Qy2NPGZhW3",
    "symbol": "SKR",
    "name": "Seeker",
    "liquidity": 1201984.810577775,
    "holderCount": 33345,
    "organicScore": 95.69369909831696,
    "topHoldersPercentage": 50.06603563644975,
    "vol1h": 367687.48908644135,
    "vol24h": 8355945.606656533,
    "traders1h": 500,
    "usdPrice": 0.02513222458664474
  },
  {
    "mint": "JUPyiwrYJFskUPiHa7hkeR8VUtAeFoSYbKedZNsDvCN",
    "symbol": "JUP",
    "name": "Jupiter",
    "liquidity": 3275300.921690568,
    "holderCount": 862068,
    "organicScore": 99.76824377172437,
    "topHoldersPercentage": 15.347695380587501,
    "vol1h": 457486.8232835794,
    "vol24h": 8286261.946650331,
    "traders1h": 578,
    "usdPrice": 0.20515307200102695
  },
  {
    "mint": "A7bdiYdS5GjqGFtxf17ppRHtDKPkkRqbKtR27dxvQXaS",
    "symbol": "ZEC",
    "name": "Zcash",
    "liquidity": 3206436.686959715,
    "holderCount": 12051,
    "organicScore": 84.62324931333329,
    "topHoldersPercentage": 29.70802419417831,
    "vol1h": 899291.3869076165,
    "vol24h": 8239044.254816429,
    "traders1h": 159,
    "usdPrice": 402.5962234483776
  },
  {
    "mint": "USoRyaQjch6E18nCdDvWoRgTo6osQs9MUd8JXEsspWR",
    "symbol": "USOR",
    "name": "U.S Oil",
    "liquidity": 426039.96483103157,
    "holderCount": 82090,
    "organicScore": 92.09513288418745,
    "topHoldersPercentage": 9.508031251917508,
    "vol1h": 430681.12643311603,
    "vol24h": 8088911.601065413,
    "traders1h": 1206,
    "usdPrice": 0.02475015163345495
  },
  {
    "mint": "GB8KtQfMChhYrCYtd5PoAB42kAdkHnuyAincSSmFpump",
    "symbol": "PIGEON",
    "name": "Pigeon Doctor ",
    "liquidity": 161120.1569247146,
    "holderCount": 2389,
    "organicScore": 89.74700185193302,
    "topHoldersPercentage": 20.24635062580288,
    "vol1h": 210071.48370232317,
    "vol24h": 4964802.036715899,
    "traders1h": 567,
    "usdPrice": 0.0013950023269236399
  },
  {
    "mint": "Dz9mQ9NzkBcCsuGPFJ3r1bS4wgqKMHBPiVuniW8Mbonk",
    "symbol": "USELESS",
    "name": "USELESS COIN",
    "liquidity": 1800509.2060631257,
    "holderCount": 37380,
    "organicScore": 91.36200536844102,
    "topHoldersPercentage": 26.971764748443672,
    "vol1h": 687597.4068884809,
    "vol24h": 4877907.679164767,
    "traders1h": 459,
    "usdPrice": 0.06808534512002548
  },
  {
    "mint": "98sMhvDwXj1RQi5c5Mndm3vPe9cBqPrbLaufMXFNMh5g",
    "symbol": "HYPE",
    "name": "HYPE",
    "liquidity": 836664.4996438352,
    "holderCount": 3677,
    "organicScore": 84.09990637429273,
    "topHoldersPercentage": 21.976441192868243,
    "vol1h": 267334.6511380477,
    "vol24h": 4708363.549351573,
    "traders1h": 138,
    "usdPrice": 30.518061334991224
  },
  {
    "mint": "2zMMhcVQEXDtdE6vsFS7S7D5oUodfJHE8vd1gnBouauv",
    "symbol": "PENGU",
    "name": "Pudgy Penguins",
    "liquidity": 4278753.6061794665,
    "holderCount": 538173,
    "organicScore": 93.12812813300576,
    "topHoldersPercentage": 50.18142024498468,
    "vol1h": 169166.6505006943,
    "vol24h": 4443417.323839791,
    "traders1h": 172,
    "usdPrice": 0.00993843516142333
  },
  {
    "mint": "2k8yZaJjf61unHriuqdmvbxe7CUhEYML5kVJDbcotKjU",
    "symbol": "BFS",
    "name": "BFS",
    "liquidity": 530215.1158068683,
    "holderCount": 70487,
    "organicScore": 85.62639483967027,
    "topHoldersPercentage": 9.065534431700438,
    "vol1h": 157832.42466996977,
    "vol24h": 4010044.723970472,
    "traders1h": 634,
    "usdPrice": 0.04266235480173919
  },
  {
    "mint": "4TyZGqRLG3VcHTGMcLBoPUmqYitMVojXinAmkL8xpump",
    "symbol": "testicle",
    "name": "testicle",
    "liquidity": 868557.534380651,
    "holderCount": 10677,
    "organicScore": 90.20873233350017,
    "topHoldersPercentage": 24.185447594892683,
    "vol1h": 188739.71295762033,
    "vol24h": 3880408.930391282,
    "traders1h": 243,
    "usdPrice": 0.00946593014071389
  },
  {
    "mint": "DezXAZ8z7PnrnRJjz3wXBoRgixCa6xjnB7YaB1pPB263",
    "symbol": "Bonk",
    "name": "Bonk",
    "liquidity": 3126985.2061047177,
    "holderCount": 992946,
    "organicScore": 92.77760530490946,
    "topHoldersPercentage": 31.15629175127636,
    "vol1h": 177951.25306233665,
    "vol24h": 3829682.7707903106,
    "traders1h": 246,
    "usdPrice": 8.85412881738038e-06
  },
  {
    "mint": "jk1T35eWK41MBMM8AWoYVaNbjHEEQzMDetTsfnqpump",
    "symbol": "SOL",
    "name": "Sol The Trophy Tomato",
    "liquidity": 276447.9704633035,
    "holderCount": 6571,
    "organicScore": 87.84805554065696,
    "topHoldersPercentage": 17.16967861088152,
    "vol1h": 63649.1040664602,
    "vol24h": 3643696.3939918587,
    "traders1h": 152,
    "usdPrice": 0.0035807173436164675
  },
  {
    "mint": "258Po41aeXsh3jyqt5TqcJ4JSQe4rnSVd9wvcNPupump",
    "symbol": "CPENG",
    "name": "Club Penguin",
    "liquidity": 53183.354095568306,
    "holderCount": 994,
    "organicScore": 70.1309250590968,
    "topHoldersPercentage": 17.133250646351676,
    "vol1h": 35725.61256244988,
    "vol24h": 3638002.3713770034,
    "traders1h": 124,
    "usdPrice": 0.0008524887054080092
  },
  {
    "mint": "4vGHdzcNrDf8XVE8H19Rqea86RULz7xi89ew1sSJpump",
    "symbol": "21",
    "name": "2131KOBUSHIDE",
    "liquidity": 181314.54736032733,
    "holderCount": 11160,
    "organicScore": 81.13020305528815,
    "topHoldersPercentage": 14.457546746011202,
    "vol1h": 102737.81449940137,
    "vol24h": 3405717.557234854,
    "traders1h": 516,
    "usdPrice": 0.005069830233570687
  },
  {
    "mint": "BBKPiLM9KjdJW7oQSKt99RVWcZdhF6sEHRKnwqeBGHST",
    "symbol": "GHOST",
    "name": "GhostwareOS",
    "liquidity": 316442.6500385009,
    "holderCount": 16194,
    "organicScore": 89.71049290665903,
    "topHoldersPercentage": 13.915209811981052,
    "vol1h": 88007.35763357196,
    "vol24h": 3302062.4073908813,
    "traders1h": 388,
    "usdPrice": 0.009885797506833282
  },
  {
    "mint": "4gfNpwo8LQtcgGrNmgWhuwfFhttgZ8Qb6QXN4Yz8BAGS",
    "symbol": "EVA",
    "name": "Eva Everywhere",
    "liquidity": 195359.93437135633,
    "holderCount": 2373,
    "organicScore": 87.02593936673,
    "topHoldersPercentage": 17.19606546376514,
    "vol1h": 203409.3513249512,
    "vol24h": 3239485.014571652,
    "traders1h": 442,
    "usdPrice": 0.0030254161677882125
  },
  {
    "mint": "Cm6fNnMk7NfzStP9CZpsQA2v3jjzbcYGAxdJySmHpump",
    "symbol": "Buttcoin",
    "name": "Buttcoin",
    "liquidity": 586816.4909275875,
    "holderCount": 7633,
    "organicScore": 86.7497196112467,
    "topHoldersPercentage": 14.776923773808933,
    "vol1h": 59905.79722102301,
    "vol24h": 3120753.7642170107,
    "traders1h": 187,
    "usdPrice": 0.005069176562029455
  },
  {
    "mint": "8J69rbLTzWWgUJziFY8jeu5tDwEPBwUz4pKBMr5rpump",
    "symbol": "WOJAK",
    "name": "Wojak ",
    "liquidity": 855202.6937800894,
    "holderCount": 13294,
    "organicScore": 86.13778471813328,
    "topHoldersPercentage": 15.448375399732782,
    "vol1h": 63276.753609475425,
    "vol24h": 2557008.201628062,
    "traders1h": 160,
    "usdPrice": 0.0104642737479067
  },
  {
    "mint": "8AdsF2QXFA8QkFuQ9TrQW6nEyM4E6yT4AwqgZ5cTpump",
    "symbol": "ALONE",
    "name": "forever alone",
    "liquidity": 227902.0686452642,
    "holderCount": 1894,
    "organicScore": 82.86963447045076,
    "topHoldersPercentage": 10.165663391221337,
    "vol1h": 133673.3790672745,
    "vol24h": 2409073.796693481,
    "traders1h": 284,
    "usdPrice": 0.008395220043805064
  },
  {
    "mint": "2nP9yKQNSGQy851iyawDvBkzkK2R2aqKArQCKc2gpump",
    "symbol": "PsyopAnime",
    "name": "PsyopAnime",
    "liquidity": 534103.3444199673,
    "holderCount": 10065,
    "organicScore": 86.17381071359573,
    "topHoldersPercentage": 16.001981379009596,
    "vol1h": 162629.31157334815,
    "vol24h": 2318595.936934906,
    "traders1h": 296,
    "usdPrice": 0.005430262119056183
  },
  {
    "mint": "Av3cLhrHypqqh5VNqgmASeCGKbPGB8L2teNRuhH3bonk",
    "symbol": "BWT",
    "name": "Barron Meme",
    "liquidity": 81936.07282178907,
    "holderCount": 2303,
    "organicScore": 75.0,
    "topHoldersPercentage": 16.303069279006365,
    "vol1h": 22298.051231708385,
    "vol24h": 2112909.595467095,
    "traders1h": 126,
    "usdPrice": 0.0008344664344015494
  },
  {
    "mint": "8opvqaWysX1oYbXuTL8PHaoaTiXD69VFYAX4smPebonk",
    "symbol": "WAR",
    "name": "WAR",
    "liquidity": 167316.26779655027,
    "holderCount": 3836,
    "organicScore": 76.19984063148391,
    "topHoldersPercentage": 13.80051403777149,
    "vol1h": 135584.37947834845,
    "vol24h": 2012614.8976140574,
    "traders1h": 244,
    "usdPrice": 0.008783079896214324
  },
  {
    "mint": "4nswj3o1Lo9iWYvvRJxUD8vbCy9ay7QQoXYcncHNbonk",
    "symbol": "SPSC",
    "name": "Shit Piss Skin Can",
    "liquidity": 166120.74536183532,
    "holderCount": 4853,
    "organicScore": 83.31388245010106,
    "topHoldersPercentage": 12.545831298162186,
    "vol1h": 103509.60057618748,
    "vol24h": 1835637.114379603,
    "traders1h": 259,
    "usdPrice": 0.0014506060425860665
  },
  {
    "mint": "5UUH9RTDiSpq6HKS6bp4NdU9PNJpXRXuiw6ShBTBhgH2",
    "symbol": "TROLL",
    "name": "TROLL",
    "liquidity": 1197947.9742268457,
    "holderCount": 49526,
    "organicScore": 87.08740900019376,
    "topHoldersPercentage": 25.836268219084484,
    "vol1h": 57302.87423255817,
    "vol24h": 1802032.6685189295,
    "traders1h": 125,
    "usdPrice": 0.024233521557424642
  },
  {
    "mint": "BANKJmvhT8tiJRsBSS1n2HryMBPvT5Ze4HU95DUAmeta",
    "symbol": "AVICI",
    "name": "Avici",
    "liquidity": 2220780.233979773,
    "holderCount": 14061,
    "organicScore": 85.11587909354103,
    "topHoldersPercentage": 16.36379653619178,
    "vol1h": 84841.49471475465,
    "vol24h": 1732898.6063039922,
    "traders1h": 130,
    "usdPrice": 1.9535948488716968
  },
  {
    "mint": "AWc8uws9nh7pYjFQ8FzxavmP8WTUPwmQZAvK2yAPBAGS",
    "symbol": "ZHC",
    "name": "ZERO-HUMAN COMPANY",
    "liquidity": 119258.12098004011,
    "holderCount": 2296,
    "organicScore": 80.60308513849081,
    "topHoldersPercentage": 20.20790078793385,
    "vol1h": 43705.113119915666,
    "vol24h": 1715908.3358224062,
    "traders1h": 164,
    "usdPrice": 0.0020864912463341083
  },
  {
    "mint": "J3NKxxXZcnNiMjKw9hYb2K4LUxgwB6t1FtPtQVsv3KFr",
    "symbol": "SPX",
    "name": "SPX6900 (Wormhole)",
    "liquidity": 2907676.759798107,
    "holderCount": 67941,
    "organicScore": 85.41465450159184,
    "topHoldersPercentage": 15.456790789675502,
    "vol1h": 24509.40778177964,
    "vol24h": 1565412.853667286,
    "traders1h": 78,
    "usdPrice": 0.39289501466026727
  },
  {
    "mint": "GMvCfcZg8YvkkQmwDaAzCtHDrrEtgE74nQpQ7xNabonk",
    "symbol": "1",
    "name": "1 coin can change your life",
    "liquidity": 459171.2371000668,
    "holderCount": 12321,
    "organicScore": 85.45994007435849,
    "topHoldersPercentage": 13.09686804242518,
    "vol1h": 44464.32988828403,
    "vol24h": 1483516.3586542148,
    "traders1h": 107,
    "usdPrice": 0.006126522242040465
  },
  {
    "mint": "PRVT6TB7uss3FrUd2D9xs2zqDBsa3GbMJMwCQsgmeta",
    "symbol": "UMBRA",
    "name": "Umbra",
    "liquidity": 2525744.1483167685,
    "holderCount": 7373,
    "organicScore": 78.89324939515546,
    "topHoldersPercentage": 55.649107476736184,
    "vol1h": 44346.45873369524,
    "vol24h": 1393104.4019467211,
    "traders1h": 41,
    "usdPrice": 1.527112875243349
  },
  {
    "mint": "61V8vBaqAGMpgDQi4JcAwo1dmBGHsyhzodcPqnEVpump",
    "symbol": "arc",
    "name": "AI Rig Complex",
    "liquidity": 3920231.0018317136,
    "holderCount": 45326,
    "organicScore": 78.08172495077802,
    "topHoldersPercentage": 12.446999694505712,
    "vol1h": 37891.80157953473,
    "vol24h": 1383256.9162874767,
    "traders1h": 73,
    "usdPrice": 0.05206445692194708
  },
  {
    "mint": "EKpQGSJtjMFqKZ9KQanSqYXRcF8fBopzLHYxdM65zcjm",
    "symbol": "$WIF",
    "name": "dogwifhat",
    "liquidity": 8252484.886238149,
    "holderCount": 253771,
    "organicScore": 78.12558950537392,
    "topHoldersPercentage": 17.155592458640072,
    "vol1h": 34204.178774030974,
    "vol24h": 1361716.4920887882,
    "traders1h": 143,
    "usdPrice": 0.3268265794466546
  },
  {
    "mint": "7MDApufGNAKDDTcM3hrUpUfZ8jcaXdaoSZy1sQdRpump",
    "symbol": "Dale",
    "name": "Dale",
    "liquidity": 46980.942014081535,
    "holderCount": 4845,
    "organicScore": 75.0,
    "topHoldersPercentage": 16.35212901891575,
    "vol1h": 29649.358553813217,
    "vol24h": 1319336.028512658,
    "traders1h": 170,
    "usdPrice": 0.0004420330184427151
  },
  {
    "mint": "XsDoVfqeBukxuZHWhdvWHBhgEHjGNst4MLodqsJHzoB",
    "symbol": "TSLAx",
    "name": "Tesla xStock",
    "liquidity": 1134031.1079789675,
    "holderCount": 18964,
    "organicScore": 75.0,
    "topHoldersPercentage": 48.33888807588214,
    "vol1h": 25822.377527880697,
    "vol24h": 1300480.4936681786,
    "traders1h": 40,
    "usdPrice": 431.8190559308391
  },
  {
    "mint": "x95HN3DWvbfCBtTjGm587z8suK3ec6cwQwgZNLbWKyp",
    "symbol": "$HACHI",
    "name": "Hachiko",
    "liquidity": 232271.25319902258,
    "holderCount": 31508,
    "organicScore": 80.16067873317266,
    "topHoldersPercentage": 11.002316081181498,
    "vol1h": 24005.414384068044,
    "vol24h": 1292758.7700772565,
    "traders1h": 250,
    "usdPrice": 9.001193576979105e-09
  },
  {
    "mint": "GASfLqDbE8c9w8mjKknxaHeDMmdy9usGwM1GwzVJpump",
    "symbol": "Mountain",
    "name": "The Mountain",
    "liquidity": 65405.07886519855,
    "holderCount": 7516,
    "organicScore": 81.20857404805417,
    "topHoldersPercentage": 15.126469706931173,
    "vol1h": 43546.616666196045,
    "vol24h": 1230508.2279906464,
    "traders1h": 224,
    "usdPrice": 0.0005946626193918062
  },
  {
    "mint": "DMYNp65mub3i7LRpBdB66CgBAceLcQnv4gsWeCi6pump",
    "symbol": "丙午",
    "name": "bǐngwǔ",
    "liquidity": 130113.11267317615,
    "holderCount": 6023,
    "organicScore": 80.65335119018448,
    "topHoldersPercentage": 18.729069371987208,
    "vol1h": 37516.38584095803,
    "vol24h": 1153037.911472542,
    "traders1h": 226,
    "usdPrice": 0.002522795779428369
  },
  {
    "mint": "rndrizKT3MK1iimdxRdWabcF7Zg7AR5T4nud4EkHBof",
    "symbol": "RENDER",
    "name": "Render Token",
    "liquidity": 220673.1462157089,
    "holderCount": 114820,
    "organicScore": 75.0,
    "topHoldersPercentage": 40.370169036480725,
    "vol1h": 8051.735415238826,
    "vol24h": 1101756.8856537337,
    "traders1h": 28,
    "usdPrice": 1.8667196408628042
  },
  {
    "mint": "oreoU2P8bN6jkk3jbaiVxYnG1dCXcYxwhwyK9jSybcp",
    "symbol": "ORE",
    "name": "ORE",
    "liquidity": 460129.8079763617,
    "holderCount": 27085,
    "organicScore": 82.29253289311373,
    "topHoldersPercentage": 45.56533586079539,
    "vol1h": 60344.178848527365,
    "vol24h": 1097364.738930348,
    "traders1h": 125,
    "usdPrice": 111.57655201503393
  },
  {
    "mint": "J6pQQ3FAcJQeWPPGppWRb4nM8jU3wLyYbRrLh7feMfvd",
    "symbol": "2Z",
    "name": "DoubleZero",
    "liquidity": 818771.6138963142,
    "holderCount": 6395,
    "organicScore": 65.56132404221266,
    "topHoldersPercentage": 51.68641373783037,
    "vol1h": 21034.04816365427,
    "vol24h": 1095913.3319509595,
    "traders1h": 31,
    "usdPrice": 0.11912748846974763
  },
  {
    "mint": "Bx3REmoo2J4t4K6JF83AbQTkY8C6G6sc7TyyaCe8surg",
    "symbol": "Unicorn",
    "name": "Unicorn",
    "liquidity": 69264.61567719898,
    "holderCount": 1547,
    "organicScore": 76.16867958349386,
    "topHoldersPercentage": 20.640507059069865,
    "vol1h": 29046.104678726384,
    "vol24h": 1092121.6762995734,
    "traders1h": 128,
    "usdPrice": 0.0012250690609586449
  },
  {
    "mint": "ZBCNpuD7YMXzTHB2fhGkGi78MNsHGLRXUhRewNRm9RU",
    "symbol": "ZBCN",
    "name": "Zebec Network",
    "liquidity": 190152.25231489804,
    "holderCount": 93298,
    "organicScore": 76.71270351283951,
    "topHoldersPercentage": 46.832427856976224,
    "vol1h": 11497.046691685326,
    "vol24h": 1049514.9790064152,
    "traders1h": 45,
    "usdPrice": 0.002787575530468955
  },
  {
    "mint": "GMzuntWYJLpNuCizrSR7ZXggiMdDzTNiEmSNHHunpump",
    "symbol": "dreams",
    "name": "Daydreams",
    "liquidity": 419736.4815758577,
    "holderCount": 5959,
    "organicScore": 78.29421322097822,
    "topHoldersPercentage": 35.842680557659435,
    "vol1h": 23626.364396426354,
    "vol24h": 1015922.1582257521,
    "traders1h": 38,
    "usdPrice": 0.013252378462256548
  },
  {
    "mint": "jtojtomepa8beP8AuQc6eXt5FriJwfFMwQx2v2f9mCL",
    "symbol": "JTO",
    "name": "JITO",
    "liquidity": 158935.2807638924,
    "holderCount": 80960,
    "organicScore": 74.94399863045025,
    "topHoldersPercentage": 46.25008336907587,
    "vol1h": 19060.98615183433,
    "vol24h": 449189.85519149667,
    "traders1h": 44,
    "usdPrice": 0.364708562509967
  },
  {
    "mint": "5Lnq4beU4ZYodKeQw741XumFERyTAcKvpg6WNHzDpump",
    "symbol": "Grokipedia",
    "name": "Grokipedia",
    "liquidity": 54157.22215798349,
    "holderCount": 4481,
    "organicScore": 59.940492099256254,
    "topHoldersPercentage": 22.622681692882086,
    "vol1h": 243360.6333900025,
    "vol24h": 970064.7361129597,
    "traders1h": 2025,
    "usdPrice": 0.0009392931335800862
  },
  {
    "mint": "1zJX5gRnjLgmTpq5sVwkq69mNDQkCemqoasyjaPW6jm",
    "symbol": "KLED",
    "name": "KLEDAI",
    "liquidity": 636680.4928161337,
    "holderCount": 10623,
    "organicScore": 75.0,
    "topHoldersPercentage": 25.037849706233768,
    "vol1h": 24972.27580221655,
    "vol24h": 461351.7927318114,
    "traders1h": 35,
    "usdPrice": 0.027416190800407733
  },
  {
    "mint": "nosXBVoaCTtYdLvKY6Csb4AC8JCdQKKAaWYtx2ZMoo7",
    "symbol": "NOS",
    "name": "Nosana",
    "liquidity": 295619.31483727484,
    "holderCount": 49119,
    "organicScore": 72.21730493756931,
    "topHoldersPercentage": 40.21916493339155,
    "vol1h": 14216.613799800793,
    "vol24h": 62445.64799401746,
    "traders1h": 29,
    "usdPrice": 0.2340082148342809
  },
  {
    "mint": "6nR8wBnfsmXfcdDr1hovJKjvFQxNSidN6XFyfAFZpump",
    "symbol": "Clash",
    "name": "GeorgePlaysClashRoyale",
    "liquidity": 460279.1480945418,
    "holderCount": 7522,
    "organicScore": 70.32769629848448,
    "topHoldersPercentage": 27.761459083529676,
    "vol1h": 10710.040887295318,
    "vol24h": 265326.31675244484,
    "traders1h": 34,
    "usdPrice": 0.049544004456947684
  },
  {
    "mint": "DuMbhu7mvQvqQHGcnikDgb4XegXJRyhUBfdU22uELiZA",
    "symbol": "elizaOS",
    "name": "elizaOS",
    "liquidity": 75048.20911993674,
    "holderCount": 6273,
    "organicScore": 69.12126545662872,
    "topHoldersPercentage": 44.104785553477235,
    "vol1h": 11416.772425250074,
    "vol24h": 134079.96527077956,
    "traders1h": 27,
    "usdPrice": 0.0021800473579944813
  },
  {
    "mint": "GkyPYa7NnCFbduLknCfBfP7p8564X1VZhwZYJ6CZpump",
    "symbol": "CHILLHOUSE",
    "name": "Chill House",
    "liquidity": 364695.74847287737,
    "holderCount": 15883,
    "organicScore": 67.4734530211828,
    "topHoldersPercentage": 23.36038418625408,
    "vol1h": 17332.148137910426,
    "vol24h": 161781.01031014143,
    "traders1h": 34,
    "usdPrice": 0.004201578340120873
  },
  {
    "mint": "DtR4D9FtVoTX2569gaL837ZgrB6wNjj6tkmnX9Rdk9B2",
    "symbol": "aura",
    "name": "aura",
    "liquidity": 1008907.7081346733,
    "holderCount": 36350,
    "organicScore": 75.0,
    "topHoldersPercentage": 9.872309349073857,
    "vol1h": 11155.453248007854,
    "vol24h": 211174.08413168753,
    "traders1h": 30,
    "usdPrice": 0.017833929138342343
  },
  {
    "mint": "MEW1gQWJ3nEXg2qgERiKu7FAFj79PHvQVREQUzScPP5",
    "symbol": "MEW",
    "name": "cat in a dogs world",
    "liquidity": 14183436.343645144,
    "holderCount": 161712,
    "organicScore": 67.03901276014548,
    "topHoldersPercentage": 53.73459171611253,
    "vol1h": 5479.230665821746,
    "vol24h": 392498.39519412804,
    "traders1h": 30,
    "usdPrice": 0.000906109804229481
  },
  {
    "mint": "89q6aHpZ1fXhuwpnrBgqmCvuAX4GaCrRPQNp5xVHpump",
    "symbol": "CONCHO",
    "name": "hispanic pepe",
    "liquidity": 70200.76923347266,
    "holderCount": 9856,
    "organicScore": 63.08216058529872,
    "topHoldersPercentage": 18.79215030600157,
    "vol1h": 9532.156640610401,
    "vol24h": 96278.56649969841,
    "traders1h": 30,
    "usdPrice": 0.0003375957759796501
  },
  {
    "mint": "9NrkmoqwF1rBjsfKZvn7ngCy6zqvb8A6A5RfTvR2pump",
    "symbol": "SS",
    "name": "somaliscan",
    "liquidity": 80650.43817606958,
    "holderCount": 2651,
    "organicScore": 60.289096432325934,
    "topHoldersPercentage": 39.935606569778685,
    "vol1h": 9085.538633016473,
    "vol24h": 124331.87402530567,
    "traders1h": 37,
    "usdPrice": 0.0012978318172560555
  },
  {
    "mint": "Dq3Fwkvo9zC87RmZ6ZKEYiztnAyr6qX9wmYjHJgiBAGS",
    "symbol": "GOLEM",
    "name": "Golem",
    "liquidity": 55771.793218800296,
    "holderCount": 1417,
    "organicScore": 68.42831974315425,
    "topHoldersPercentage": 23.061142187445927,
    "vol1h": 8990.478556205751,
    "vol24h": 272782.3704850528,
    "traders1h": 31,
    "usdPrice": 0.00040110694051500516
  },
  {
    "mint": "DSXSpV5k2UoM5xYk7fxQZR3a9h8JiwPEifg8gajPpump",
    "symbol": "lockin",
    "name": "the time is now retard",
    "liquidity": 77755.80827295929,
    "holderCount": 2849,
    "organicScore": 52.96631104707504,
    "topHoldersPercentage": 9.768395023151456,
    "vol1h": 190274.8470829905,
    "vol24h": 502283.63945659646,
    "traders1h": 1879,
    "usdPrice": 0.002640379686915109
  },
  {
    "mint": "4SDfM29FFTmQDGKBHtThh9oYhdRcwPSTqYVgJ6EtyLSD",
    "symbol": "$LSD",
    "name": "LSD",
    "liquidity": 78744.63082381678,
    "holderCount": 4250,
    "organicScore": 62.81859048379318,
    "topHoldersPercentage": 16.216123010520363,
    "vol1h": 363610.4015779563,
    "vol24h": 610087.2693679992,
    "traders1h": 737,
    "usdPrice": 0.0023849069659237256
  },
  {
    "mint": "5zCETicUCJqJ5Z3wbfFPZqtSpHPYqnggs1wX7ZRpump",
    "symbol": "SPARK",
    "name": "Illusion of Life",
    "liquidity": 200335.43835484178,
    "holderCount": 12751,
    "organicScore": 66.56119825298934,
    "topHoldersPercentage": 15.177354299516349,
    "vol1h": 9731.06724604054,
    "vol24h": 149660.06724493043,
    "traders1h": 36,
    "usdPrice": 0.0019680616552381785
  },
  {
    "mint": "FyPDfX92B4uEk4zZouy96d1Kk1LgnCznBpzAFSsZpump",
    "symbol": "Mia",
    "name": "Mia Ko",
    "liquidity": 131932.8890675264,
    "holderCount": 5344,
    "organicScore": 73.13013653761958,
    "topHoldersPercentage": 15.539199980434015,
    "vol1h": 14857.675253669757,
    "vol24h": 483664.7444615952,
    "traders1h": 54,
    "usdPrice": 0.0011592055430537957
  },
  {
    "mint": "8116V1BW9zaXUM6pVhWVaAduKrLcEBi3RGXedKTrBAGS",
    "symbol": "GSD",
    "name": "Get Shit Done",
    "liquidity": 133815.61675502063,
    "holderCount": 3258,
    "organicScore": 80.54317807846424,
    "topHoldersPercentage": 19.211022591409197,
    "vol1h": 24331.838525754836,
    "vol24h": 923009.8461737188,
    "traders1h": 108,
    "usdPrice": 0.0017834145403258239
  },
  {
    "mint": "2LzLh5pHg3nDQz6goTLAvDXfDbSBgAR8qem3bdXdpump",
    "symbol": "JUICE",
    "name": "JUICE",
    "liquidity": 78780.36460942918,
    "holderCount": 950,
    "organicScore": 57.24741030683315,
    "topHoldersPercentage": 20.412790892342557,
    "vol1h": 6094.146972868385,
    "vol24h": 92290.55441919844,
    "traders1h": 43,
    "usdPrice": 0.0014103932042823886
  },
  {
    "mint": "6ogzHhzdrQr9Pgv6hZ2MNze7UrzBMAFyBBWUYp1Fhitx",
    "symbol": "RETARDIO",
    "name": "RETARDIO",
    "liquidity": 250748.65000675753,
    "holderCount": 43003,
    "organicScore": 72.26094337393687,
    "topHoldersPercentage": 19.693312335371722,
    "vol1h": 5430.991158944488,
    "vol24h": 80578.37212708045,
    "traders1h": 35,
    "usdPrice": 0.002736123517875246
  },
  {
    "mint": "So11111111111111111111111111111111111111112",
    "symbol": "SOL",
    "name": "Wrapped SOL",
    "liquidity": 148793295.31283617,
    "holderCount": 3820662,
    "organicScore": 99.28326842959358,
    "topHoldersPercentage": 0.5950448622748574,
    "vol1h": 767676192.9644234,
    "vol24h": 13955126703.94903,
    "traders1h": 169095,
    "usdPrice": 127.20031617494882
  },
  {
    "mint": "EPjFWdd5AufqSSqeM2qN1xzybapC8G4wEGGkZwyTDt1v",
    "symbol": "USDC",
    "name": "USD Coin",
    "liquidity": 4167274.744795802,
    "holderCount": 5248202,
    "organicScore": 100.0,
    "topHoldersPercentage": 23.54699050390982,
    "vol1h": 147325626.2116307,
    "vol24h": 4163257427.563427,
    "traders1h": 13636,
    "usdPrice": 0.9995408990466912
  },
  {
    "mint": "Es9vMFrzaCERmJfrF4H2FYD4KCoNkY11McCe8BenwNYB",
    "symbol": "USDT",
    "name": "USDT",
    "liquidity": 13956509.508969279,
    "holderCount": 2305507,
    "organicScore": 100.0,
    "topHoldersPercentage": 38.21487337794574,
    "vol1h": 20722545.57495985,
    "vol24h": 803772412.8604064,
    "traders1h": 3818,
    "usdPrice": 0.9985673456936266
  },
  {
    "mint": "USD1ttGY1N17NEEHLmELoaybftRBUSErhqYiQzvEmuB",
    "symbol": "USD1",
    "name": "World Liberty Financial USD",
    "liquidity": 15438775.552695842,
    "holderCount": 203746,
    "organicScore": 95.4456604299839,
    "topHoldersPercentage": 7.670125381021117,
    "vol1h": 12941012.949148174,
    "vol24h": 211317150.69985178,
    "traders1h": 4051,
    "usdPrice": 0.999671547051374
  },
  {
    "mint": "7vfCXTUXx5WJV5JADk17DUJ4ksgau7utNKj4b963voxs",
    "symbol": "ETH",
    "name": "Ether (Portal)",
    "liquidity": 21907834.515228294,
    "holderCount": 104423,
    "organicScore": 98.05650804442735,
    "topHoldersPercentage": 7.7729433687940785,
    "vol1h": 1123229.5059166783,
    "vol24h": 29992949.795330964,
    "traders1h": 378,
    "usdPrice": 3010.0408741754586
  },
  {
    "mint": "J1toso1uCk3RLmjorhTtrVwY9HJ7X8V9yYac6Y7kGCPn",
    "symbol": "JitoSOL",
    "name": "Jito Staked SOL",
    "liquidity": 1824194227.7658648,
    "holderCount": 192667,
    "organicScore": 98.28847917667528,
    "topHoldersPercentage": 32.32860269808295,
    "vol1h": 257123.0185888958,
    "vol24h": 11741076.680288354,
    "traders1h": 233,
    "usdPrice": 160.03534944945082
  },
  {
    "mint": "jupSoLaHXQiZZTSfEWMTRRgpnyFm8f6sZdosWBjx93v",
    "symbol": "JupSOL",
    "name": "Jupiter Staked SOL",
    "liquidity": 634344504.5061921,
    "holderCount": 32870,
    "organicScore": 92.12763229777225,
    "topHoldersPercentage": 30.73252378312416,
    "vol1h": 38143.90919035501,
    "vol24h": 5683789.444577936,
    "traders1h": 65,
    "usdPrice": 148.3372042711689
  },
  {
    "mint": "8TuHAfTBTMW1fJNq5bNoeX4zhk2492DNsCgVSYzApump",
    "symbol": "AMELIA",
    "name": "Amelia the Patriot",
    "liquidity": 64799.60035912081,
    "holderCount": 2921,
    "organicScore": 75.0,
    "topHoldersPercentage": 18.915560106040562,
    "vol1h": 16794.054682299713,
    "vol24h": 724673.4866238101,
    "traders1h": 73,
    "usdPrice": 0.0007864916326372899
  },
  {
    "mint": "kMKX8hBaj3BTRBbeYix9c16EieBP5dih8DTSSwCpump",
    "symbol": "afk",
    "name": "afk",
    "liquidity": 62448.26217560781,
    "holderCount": 866,
    "organicScore": 74.12201002483219,
    "topHoldersPercentage": 20.868135729549675,
    "vol1h": 13541.4959976787,
    "vol24h": 805160.8574799837,
    "traders1h": 57,
    "usdPrice": 0.0013618569608019578
  },
  {
    "mint": "H5hygVvXiYxk2a3BVtjiqcDJK8TdHTB5u5U1fXEuBAGS",
    "symbol": "PRIVACY",
    "name": "PrivacyDex",
    "liquidity": 47141.347800312964,
    "holderCount": 18018,
    "organicScore": 78.67323498093802,
    "topHoldersPercentage": 34.99602614020117,
    "vol1h": 8810.147107147483,
    "vol24h": 420244.684219685,
    "traders1h": 65,
    "usdPrice": 0.000823298262580406
  }
]